{"data":{"count":3,"list":[{"pct":-1.83,"symbol":"SZ300507","pettm":49.505,"chgpct":10.18,"type":11,"areacode":"320000","tick_size":0.01,"has_follow":false,"current":8.58,"mc":6834389622,"name":"苏奥传感","pct10":20.33660589060309,"exchange":"sh_sz","tr":18.29,"indcode":"S2802"},{"pct":-3.97,"symbol":"SZ002730","pettm":71.689,"chgpct":7.85,"type":11,"areacode":"330000","tick_size":0.01,"has_follow":false,"current":18.36,"mc":6647786597,"name":"电光科技","pct10":24.64358452138492,"exchange":"sh_sz","tr":21.28,"indcode":"S6402"},{"pct":2.21,"symbol":"SH600105","pettm":33.405,"chgpct":7.18,"type":11,"areacode":"320000","tick_size":0.01,"has_follow":false,"current":7.4,"mc":10818761535,"name":"永鼎股份","pct10":32.61648745519714,"exchange":"sh_sz","tr":15.98,"indcode":"S7302"}]},"error_code":0,"error_description":""}