{"data":{"count":2,"list":[{"pct":-11.09,"symbol":"SZ300674","pettm":52.975,"chgpct":11.42,"type":11,"areacode":"110000","tick_size":0.01,"has_follow":false,"current":24.38,"mc":17164911123,"name":"宇信科技","pct10":28.315789473684205,"exchange":"sh_sz","tr":15.31,"indcode":"S7103"},{"pct":10,"symbol":"SH600217","pettm":53.944,"chgpct":10,"type":11,"areacode":"610000","tick_size":0.01,"has_follow":false,"current":7.04,"mc":11669881858,"name":"中再资环","pct10":25.04440497335702,"exchange":"sh_sz","tr":15.39,"indcode":"S7601"}]},"error_code":0,"error_description":""}