{"data":{"count":4,"list":[{"pct":6.25,"symbol":"SZ301507","pettm":56.38,"chgpct":9.34,"type":11,"areacode":"330000","tick_size":0.01,"has_follow":false,"current":14.11,"mc":5030981596,"name":"民生健康","pct10":23.447069116360453,"exchange":"sh_sz","tr":16.92,"indcode":"S3701"},{"pct":4.93,"symbol":"SZ300133","pettm":61.06,"chgpct":11.95,"type":11,"areacode":"330000","tick_size":0.01,"has_follow":false,"current":8.52,"mc":16197147933,"name":"华策影视","pct10":20.16925246826516,"exchange":"sh_sz","tr":17.63,"indcode":"S7206"},{"pct":-2.62,"symbol":"SZ002590","pettm":25.729,"chgpct":7.8,"type":11,"areacode":"330000","tick_size":0.01,"has_follow":false,"current":18.22,"mc":8739166992,"name":"万安科技","pct10":36.479400749063664,"exchange":"sh_sz","tr":18.1,"indcode":"S2802"},{"pct":10.03,"symbol":"SZ001696","pettm":38.93,"chgpct":8.38,"type":11,"areacode":"500000","tick_size":0.01,"has_follow":false,"current":12.61,"mc":14438789461,"name":"宗申动力","pct10":34.72222222222223,"exchange":"sh_sz","tr":20.51,"indcode":"S6401"}]},"error_code":0,"error_description":""}