{"data":{"count":2,"list":[{"pct":7.09,"symbol":"SZ301389","pettm":57.045,"chgpct":9.99,"type":11,"areacode":"320000","tick_size":0.01,"has_follow":false,"current":19.18,"mc":5437530000,"name":"隆扬电子","pct10":35.835694050991506,"exchange":"sh_sz","tr":23.52,"indcode":"S2705"},{"pct":2.9,"symbol":"SZ300684","pettm":74.536,"chgpct":8.4,"type":11,"areacode":"110000","tick_size":0.01,"has_follow":false,"current":20.57,"mc":6160904717,"name":"中石科技","pct10":29.94314592545799,"exchange":"sh_sz","tr":15.2,"indcode":"S2706"}]},"error_code":0,"error_description":""}