{"data":{"count":2,"list":[{"pct":4.46,"symbol":"SZ300403","pettm":25.375,"chgpct":9.13,"type":11,"areacode":"440000","tick_size":0.01,"has_follow":false,"current":10.3,"mc":6210900000,"name":"汉宇集团","pct10":23.205741626794275,"exchange":"sh_sz","tr":20.33,"indcode":"S3306"},{"pct":9.4,"symbol":"SZ002264","pettm":23.844,"chgpct":10.83,"type":11,"areacode":"350000","tick_size":0.01,"has_follow":false,"current":7.68,"mc":5528522972,"name":"新华都","pct10":33.565217391304344,"exchange":"sh_sz","tr":16.13,"indcode":"S7205"}]},"error_code":0,"error_description":""}