{"data":{"count":2,"list":[{"pct":-1.32,"symbol":"SZ301091","pettm":43.58,"chgpct":10.12,"type":11,"areacode":"440000","tick_size":0.01,"has_follow":false,"current":23.9,"mc":7456800000,"name":"深城交","pct10":32.48337028824834,"exchange":"sh_sz","tr":15.36,"indcode":"S6206"},{"pct":6.24,"symbol":"SH603158","pettm":38.989,"chgpct":8.61,"type":11,"areacode":"320000","tick_size":0.01,"has_follow":false,"current":12.59,"mc":6179163263,"name":"腾龙股份","pct10":42.42081447963801,"exchange":"sh_sz","tr":22.84,"indcode":"S2802"}]},"error_code":0,"error_description":""}