{"data":{"count":4,"list":[{"pct":6.49,"symbol":"SZ002803","pettm":47.065,"chgpct":11.87,"type":11,"areacode":"350000","tick_size":0.01,"has_follow":false,"current":22.16,"mc":8385549822,"name":"吉宏股份","pct10":32.853717026378895,"exchange":"sh_sz","tr":22.79,"indcode":"S4506"},{"pct":9.44,"symbol":"SZ002351","pettm":53.974,"chgpct":10.83,"type":11,"areacode":"440000","tick_size":0.01,"has_follow":false,"current":14.15,"mc":12580864050,"name":"漫步者","pct10":36.979670861568245,"exchange":"sh_sz","tr":16.14,"indcode":"S2705"},{"pct":10,"symbol":"SZ002315","pettm":25.953,"chgpct":11.75,"type":11,"areacode":"320000","tick_size":0.01,"has_follow":false,"current":25.08,"mc":7796163320,"name":"焦点科技","pct10":32.27848101265821,"exchange":"sh_sz","tr":22.52,"indcode":"S4506"},{"pct":3.7,"symbol":"SH603083","pettm":74.454,"chgpct":9,"type":11,"areacode":"310000","tick_size":0.01,"has_follow":false,"current":28.57,"mc":7484238369,"name":"剑桥科技","pct10":33.1934731934732,"exchange":"sh_sz","tr":16.49,"indcode":"S7302"}]},"error_code":0,"error_description":""}