{"data":{"count":2,"list":[{"pct":-9.02,"symbol":"SZ301101","pettm":30.302,"chgpct":8.18,"type":11,"areacode":"320000","tick_size":0.01,"has_follow":false,"current":25.02,"mc":5041832742,"name":"明月镜片","pct10":22.227650219833908,"exchange":"sh_sz","tr":16.34,"indcode":"S3605"},{"pct":6.76,"symbol":"SH600650","pettm":42.658,"chgpct":10.69,"type":11,"areacode":"310000","tick_size":0.01,"has_follow":false,"current":13.58,"mc":7490865253,"name":"锦江在线","pct10":24.81617647058823,"exchange":"sh_sz","tr":19.02,"indcode":"S4209"}]},"error_code":0,"error_description":""}