{"data":{"count":2,"list":[{"pct":0.4,"symbol":"SZ301091","pettm":38.583,"chgpct":9.56,"type":11,"areacode":"440000","tick_size":0.01,"has_follow":false,"current":27.41,"mc":5701280000,"name":"深城交","pct10":40.420081967213115,"exchange":"sh_sz","tr":19.09,"indcode":"S6206"},{"pct":7.78,"symbol":"SZ002166","pettm":56.718,"chgpct":9.68,"type":11,"areacode":"450000","tick_size":0.01,"has_follow":false,"current":13.58,"mc":7675616169,"name":"莱茵生物","pct10":38.14852492370295,"exchange":"sh_sz","tr":18.74,"indcode":"S3702"}]},"error_code":0,"error_description":""}