{"data":{"count":3,"list":[{"pct":1.47,"symbol":"SZ300978","pettm":61.712,"chgpct":7.62,"type":11,"areacode":"440000","tick_size":0.01,"has_follow":false,"current":20.65,"mc":8749946697,"name":"东箭科技","pct10":28.260869565217373,"exchange":"sh_sz","tr":20.56,"indcode":"S2802"},{"pct":9.98,"symbol":"SZ002026","pettm":22.843,"chgpct":9.98,"type":11,"areacode":"370000","tick_size":0.01,"has_follow":false,"current":20.06,"mc":8489917953,"name":"山东威达","pct10":44.42044636429085,"exchange":"sh_sz","tr":19.44,"indcode":"S6401"},{"pct":6.15,"symbol":"SH688697","pettm":49.189,"chgpct":8.12,"type":82,"areacode":"320000","tick_size":0.01,"has_follow":false,"current":20.01,"mc":6536600667,"name":"纽威数控","pct10":26.56546489563568,"exchange":"sh_sz","tr":16.38,"indcode":null}]},"error_code":0,"error_description":""}