{"data":{"count":2,"list":[{"pct":3.53,"symbol":"SZ000700","pettm":28.555,"chgpct":10.08,"type":11,"areacode":"320000","tick_size":0.01,"has_follow":false,"current":14.38,"mc":13201061294,"name":"模塑科技","pct10":36.17424242424242,"exchange":"sh_sz","tr":22.7,"indcode":"S2802"},{"pct":3.89,"symbol":"SZ000551","pettm":27.672,"chgpct":11.38,"type":11,"areacode":"320000","tick_size":0.01,"has_follow":false,"current":14.7,"mc":7125575776,"name":"创元科技","pct10":31.602506714413604,"exchange":"sh_sz","tr":21.12,"indcode":"S7602"}]},"error_code":0,"error_description":""}