{"data":{"count":3,"list":[{"pct":8.21,"symbol":"SZ300697","pettm":55.764,"chgpct":11.25,"type":11,"areacode":"320000","tick_size":0.01,"has_follow":false,"current":18.85,"mc":8155264000,"name":"电工合金","pct10":27.27886563133019,"exchange":"sh_sz","tr":18.53,"indcode":"S2403"},{"pct":-0.76,"symbol":"SZ300209","pettm":67.33,"chgpct":8.72,"type":11,"areacode":"430000","tick_size":0.01,"has_follow":false,"current":6.49,"mc":6026848458,"name":"有棵树","pct10":23.85496183206107,"exchange":"sh_sz","tr":16.97,"indcode":"S7104"},{"pct":0.61,"symbol":"SH603266","pettm":47.913,"chgpct":7.8,"type":11,"areacode":"330000","tick_size":0.01,"has_follow":false,"current":26.2,"mc":5210832850,"name":"天龙股份","pct10":20.349104271933854,"exchange":"sh_sz","tr":16.46,"indcode":"S2802"}]},"error_code":0,"error_description":""}