{"data":{"count":2,"list":[{"pct":10.02,"symbol":"SZ002315","pettm":29.938,"chgpct":10.97,"type":11,"areacode":"320000","tick_size":0.01,"has_follow":false,"current":28.89,"mc":8993376021,"name":"焦点科技","pct10":29.726088908845988,"exchange":"sh_sz","tr":17.15,"indcode":"S4506"},{"pct":-6.7,"symbol":"SH600105","pettm":43.26,"chgpct":10.59,"type":11,"areacode":"320000","tick_size":0.01,"has_follow":false,"current":6.96,"mc":9779858331,"name":"永鼎股份","pct10":31.818181818181813,"exchange":"sh_sz","tr":23.7,"indcode":"S7302"}]},"error_code":0,"error_description":""}