{"data":{"count":4,"list":[{"pct":3.61,"symbol":"SZ003039","pettm":50.653,"chgpct":10.36,"type":11,"areacode":"440000","tick_size":0.01,"has_follow":false,"current":21.81,"mc":13461908314,"name":"顺控发展","pct10":41.623376623376615,"exchange":"sh_sz","tr":23.69,"indcode":"S7601"},{"pct":1.3,"symbol":"SH605011","pettm":30.882,"chgpct":8.15,"type":11,"areacode":"330000","tick_size":0.01,"has_follow":false,"current":17.16,"mc":6865716000,"name":"杭州热电","pct10":21.875,"exchange":"sh_sz","tr":18.76,"indcode":"S4101"},{"pct":-6.76,"symbol":"SH603122","pettm":70.3,"chgpct":8.13,"type":11,"areacode":"310000","tick_size":0.01,"has_follow":false,"current":14.34,"mc":5708074757,"name":"合富中国","pct10":22.250639386189253,"exchange":"sh_sz","tr":22.9,"indcode":"S3704"},{"pct":-8.61,"symbol":"SH600502","pettm":11.774,"chgpct":9.21,"type":11,"areacode":"340000","tick_size":0.01,"has_follow":false,"current":7.64,"mc":13149664478,"name":"安徽建工","pct10":38.90909090909091,"exchange":"sh_sz","tr":21.82,"indcode":"S6201"}]},"error_code":0,"error_description":""}