{"data":{"count":3,"list":[{"pct":3.01,"symbol":"SZ002550","pettm":38.218,"chgpct":10.36,"type":11,"areacode":"320000","tick_size":0.01,"has_follow":false,"current":12.33,"mc":15779934000,"name":"千红制药","pct10":38.69516310461192,"exchange":"sh_sz","tr":17.44,"indcode":"S3701"},{"pct":1.27,"symbol":"SZ002393","pettm":39.73,"chgpct":8,"type":11,"areacode":"120000","tick_size":0.01,"has_follow":false,"current":27.85,"mc":7177084222,"name":"力生制药","pct10":44.07656492498709,"exchange":"sh_sz","tr":17.68,"indcode":"S3701"},{"pct":4.61,"symbol":"SZ000758","pettm":36.217,"chgpct":8.72,"type":11,"areacode":"110000","tick_size":0.01,"has_follow":false,"current":6.36,"mc":12667034365,"name":"中色股份","pct10":25.196850393700792,"exchange":"sh_sz","tr":16.15,"indcode":"S2403"}]},"error_code":0,"error_description":""}