{"data":{"count":4,"list":[{"pct":-7.99,"symbol":"SZ300697","pettm":46.655,"chgpct":8.23,"type":11,"areacode":"320000","tick_size":0.01,"has_follow":false,"current":14.75,"mc":6381440000,"name":"电工合金","pct10":33.12274368231047,"exchange":"sh_sz","tr":15.34,"indcode":"S2403"},{"pct":3.38,"symbol":"SZ002093","pettm":67.3,"chgpct":9.45,"type":11,"areacode":"350000","tick_size":0.01,"has_follow":false,"current":13.45,"mc":13550875000,"name":"国脉科技","pct10":23.735050597976084,"exchange":"sh_sz","tr":16.21,"indcode":"S7301"},{"pct":5.52,"symbol":"SZ000530","pettm":53.618,"chgpct":11.79,"type":11,"areacode":"210000","tick_size":0.01,"has_follow":false,"current":7.07,"mc":5961512424,"name":"冰山冷热","pct10":27.387387387387395,"exchange":"sh_sz","tr":24.11,"indcode":"S6401"},{"pct":10,"symbol":"SH603601","pettm":56.223,"chgpct":7.39,"type":11,"areacode":"500000","tick_size":0.01,"has_follow":false,"current":5.06,"mc":5169562991,"name":"再升科技","pct10":44.57142857142856,"exchange":"sh_sz","tr":23.74,"indcode":"S6102"}]},"error_code":0,"error_description":""}