{"data":{"count":2,"list":[{"pct":7.38,"symbol":"SZ300532","pettm":24.974,"chgpct":9.29,"type":11,"areacode":"440000","tick_size":0.01,"has_follow":false,"current":18.04,"mc":5541969133,"name":"今天国际","pct10":37.0820668693009,"exchange":"sh_sz","tr":15.1,"indcode":"S7103"},{"pct":13.32,"symbol":"SH688400","pettm":60.609,"chgpct":9.07,"type":82,"areacode":"110000","tick_size":0.01,"has_follow":false,"current":29.1,"mc":13487850000,"name":"凌云光","pct10":24.518613607188705,"exchange":"sh_sz","tr":15.4,"indcode":null}]},"error_code":0,"error_description":""}