{"data":{"count":2,"list":[{"pct":-1.75,"symbol":"SZ002889","pettm":38.585,"chgpct":8.3,"type":11,"areacode":"440000","tick_size":0.01,"has_follow":false,"current":26.39,"mc":7119031847,"name":"东方嘉盛","pct10":23.145123658422776,"exchange":"sh_sz","tr":17.4,"indcode":"S4208"},{"pct":4.77,"symbol":"SH600577","pettm":25.268,"chgpct":8.72,"type":11,"areacode":"340000","tick_size":0.01,"has_follow":false,"current":6.37,"mc":13432283153,"name":"精达股份","pct10":21.333333333333336,"exchange":"sh_sz","tr":15.26,"indcode":"S6308"}]},"error_code":0,"error_description":""}